SNOMEDCTToOWL/CompareRDF.py
SNOMEDCTToOWL/Modules.py
SNOMEDCTToOWL/OWLGraphHelper.py
SNOMEDCTToOWL/RF2Filter.py
SNOMEDCTToOWL/SNOMEDToOWL.py
SNOMEDCTToOWL/SNOMEDToOWLConstants.py
SNOMEDCTToOWL/Statistics.py
SNOMEDCTToOWL/TransformationContext.py
SNOMEDCTToOWL/__init__.py
SNOMEDCTToOWL/RF2Files/Concept.py
SNOMEDCTToOWL/RF2Files/Description.py
SNOMEDCTToOWL/RF2Files/DirectoryWalker.py
SNOMEDCTToOWL/RF2Files/Language.py
SNOMEDCTToOWL/RF2Files/RF2DictWriter.py
SNOMEDCTToOWL/RF2Files/RF2File.py
SNOMEDCTToOWL/RF2Files/Relationship.py
SNOMEDCTToOWL/RF2Files/Transitive.py
SNOMEDCTToOWL/RF2Files/__init__.py
SNOMEDCTToOWL/conf/conf.json
SNOMEDCTToOWL/conf/sct_core_gb.json
SNOMEDCTToOWL/conf/sct_core_us.json
SNOMEDCTToOWL/conf/sct_core_us_edition_variant_us_inferred.json
SNOMEDCTToOWL/conf/sct_core_us_gb.json
SNOMEDCTToOWL/conf/sct_core_us_gb_skos.json
SNOMEDCTToOWL/conf/sct_core_us_inferred.json
SNOMEDCTToOWL/conf/sct_metadata_us_gb.json
SNOMEDCTToOWL/conf/us_edition_us_inferred.json
SNOMEDToOWL-1.0.4.dist-info/AUTHORS
SNOMEDToOWL-1.0.4.dist-info/LICENSE
SNOMEDToOWL-1.0.4.dist-info/METADATA
SNOMEDToOWL-1.0.4.dist-info/WHEEL
SNOMEDToOWL-1.0.4.dist-info/entry_points.txt
SNOMEDToOWL-1.0.4.dist-info/pbr.json
SNOMEDToOWL-1.0.4.dist-info/top_level.txt
SNOMEDToOWL-1.0.4.dist-info/RECORD
