Metadata-Version: 2.1
Name: SNOMEDToOWL
Version: 1.0.4
Summary: "Spackman OWL" transformation test and validation tool
Home-page: https://github.com/hsolbrig/SNOMEDToOWL
Author: Harold Solbrig
Author-email: solbrig@jhu.edu
License: CC0 1.0 Universal
Keywords: SNOMED,OWL,RF2
Platform: UNKNOWN
Classifier: Development Status :: 6 - Mature
Classifier: Environment :: Console
Classifier: Intended Audience :: Developers
Classifier: Intended Audience :: Science/Research
Classifier: Intended Audience :: Healthcare Industry
Classifier: License :: CC0 1.0 Universal (CC0 1.0) Public Domain Dedication
Classifier: Programming Language :: Python :: 3 :: Only
Classifier: Programming Language :: Python :: 3.7
Classifier: Programming Language :: Python :: 3.8
Requires-Python: >=3.7
Requires-Dist: dirlistproc (>=1.4.5)
Requires-Dist: jsonasobj (>=1.2.1)
Requires-Dist: neurdflib-jsonld
Requires-Dist: rdflib (>=4.2.2)
